dds_sine_generator.sv
`define pi 3.14159265358979323846  // Define of  pi

module dds_sine_generator (
    input wire clk,               // System clock (e.g., 50 MHz)
    input wire reset,             // Active-high reset
    input wire [31:0] freq_tuning_word, // Frequency control (32-bit precision)
    output reg [7:0] dac_data     // 8-bit output to DAC
);

// Phase accumulator (32-bit for fine frequency resolution)
reg [31:0] phase_accumulator;

// ROM for 8-bit sine wave (256 entries, 8-bit output)
reg [7:0] sine_rom [0:255];

// Initialize ROM with sine values (precomputed)
initial begin
    integer i;
    for (i = 0; i < 256; i = i + 1) begin
        sine_rom[i] = 128 + $floor(127.0 * $sin(2.0 * `pi * i / 256.0));
    end
end

// Phase accumulation and ROM lookup
always @(posedge clk or posedge reset) begin
    if (reset) begin
        phase_accumulator <= 0;
        dac_data <= 0;
    end else begin
        // Update phase accumulator (wraps automatically)
        phase_accumulator <= phase_accumulator + freq_tuning_word;
        
        // Use top 8 bits of accumulator for ROM address
        dac_data <= sine_rom[phase_accumulator[31:24]];
    end
end

endmodule

tb_dds.v
`timescale 1ns/1ps
module tb_dds();

// Testbench signals
reg clk = 0;
reg reset = 1;
reg [31:0] freq_word = 32'h200_0000; // Tuning word for ~1.19MHz @ 50MHz clock
wire [7:0] dac_out;

// Instantiate DUT
dds_sine_generator dut (
    .clk(clk),
    .reset(reset),
    .freq_tuning_word(freq_word),
    .dac_data(dac_out)
);

// Clock generation (50MHz)
always #10 clk = ~clk; // 20ns period = 50MHz

// Initialize VCD dump
initial begin
    $dumpfile("dds_wave.vcd");
    $dumpvars(0, tb_dds); // Dump all signals
end

// Stimulus
initial begin
    #100 reset = 0; // Release reset after 100ns
    
    // Change frequency after 10us
    #10000 freq_word = 32'h400_0000; // Double frequency
    
    #20000 $finish; // Stop after 20us
end

endmodule

dds_wave.vcd
$date
	Fri Jun 20 18:12:54 2025
$end
$version
	Icarus Verilog
$end
$timescale
	1ps
$end
$scope module tb_dds $end
$var wire 8 ! dac_out [7:0] $end
$var reg 1 " clk $end
$var reg 32 # freq_word [31:0] $end
$var reg 1 $ reset $end
$scope module dut $end
$var wire 1 " clk $end
$var wire 32 % freq_tuning_word [31:0] $end
$var wire 1 $ reset $end
$var reg 8 & dac_data [7:0] $end
$var reg 32 ' phase_accumulator [31:0] $end
$scope begin $unm_blk_1 $end
$var integer 32 ( i [31:0] $end
$upscope $end
$upscope $end
$upscope $end
$enddefinitions $end
$comment Show the parameter values. $end
$dumpall
$end
#0
$dumpvars
b100000000 (
bx '
bx &
b10000000000000000000000000 %
1$
b10000000000000000000000000 #
0"
bx !
$end
#10000
b0 !
b0 &
b0 '
1"
#20000
0"
#30000
1"
#40000
0"
#50000
1"
#60000
0"
#70000
1"
#80000
0"
#90000
1"
#100000
0"
0$
#110000
b10000000 !
b10000000 &
b10000000000000000000000000 '
1"
#120000
0"
#130000
b10000110 !
b10000110 &
b100000000000000000000000000 '
1"
#140000
0"
#150000
b10001100 !
b10001100 &
b110000000000000000000000000 '
1"
#160000
0"
#170000
b10010010 !
b10010010 &
b1000000000000000000000000000 '
1"
#180000
0"
#190000
b10011000 !
b10011000 &
b1010000000000000000000000000 '
1"
#200000
0"
#210000
b10011110 !
b10011110 &
b1100000000000000000000000000 '
1"
#220000
0"
#230000
b10100100 !
b10100100 &
b1110000000000000000000000000 '
1"
#240000
0"
#250000
b10101010 !
b10101010 &
b10000000000000000000000000000 '
1"
#260000
0"
#270000
b10110000 !
b10110000 &
b10010000000000000000000000000 '
1"
#280000
0"
#290000
b10110110 !
b10110110 &
b10100000000000000000000000000 '
1"
#300000
0"
#310000
b10111011 !
b10111011 &
b10110000000000000000000000000 '
1"
#320000
0"
#330000
b11000001 !
b11000001 &
b11000000000000000000000000000 '
1"
#340000
0"
#350000
b11000110 !
b11000110 &
b11010000000000000000000000000 '
1"
#360000
0"
#370000
b11001011 !
b11001011 &
b11100000000000000000000000000 '
1"
#380000
0"
#390000
b11010000 !
b11010000 &
b11110000000000000000000000000 '
1"
#400000
0"
#410000
b11010101 !
b11010101 &
b100000000000000000000000000000 '
1"
#420000
0"
#430000
b11011001 !
b11011001 &
b100010000000000000000000000000 '
1"
#440000
0"
#450000
b11011110 !
b11011110 &
b100100000000000000000000000000 '
1"
#460000
0"
#470000
b11100010 !
b11100010 &
b100110000000000000000000000000 '
1"
#480000
0"
#490000
b11100110 !
b11100110 &
b101000000000000000000000000000 '
1"
#500000
0"
#510000
b11101001 !
b11101001 &
b101010000000000000000000000000 '
1"
#520000
0"
#530000
b11101100 !
b11101100 &
b101100000000000000000000000000 '
1"
#540000
0"
#550000
b11110000 !
b11110000 &
b101110000000000000000000000000 '
1"
#560000
0"
#570000
b11110010 !
b11110010 &
b110000000000000000000000000000 '
1"
#580000
0"
#590000
b11110101 !
b11110101 &
b110010000000000000000000000000 '
1"
#600000
0"
#610000
b11110111 !
b11110111 &
b110100000000000000000000000000 '
1"
#620000
0"
#630000
b11111001 !
b11111001 &
b110110000000000000000000000000 '
1"
#640000
0"
#650000
b11111011 !
b11111011 &
b111000000000000000000000000000 '
1"
#660000
0"
#670000
b11111100 !
b11111100 &
b111010000000000000000000000000 '
1"
#680000
0"
#690000
b11111101 !
b11111101 &
b111100000000000000000000000000 '
1"
#700000
0"
#710000
b11111110 !
b11111110 &
b111110000000000000000000000000 '
1"
#720000
0"
#730000
b1000000000000000000000000000000 '
1"
#740000
0"
#750000
b11111111 !
b11111111 &
b1000010000000000000000000000000 '
1"
#760000
0"
#770000
b11111110 !
b11111110 &
b1000100000000000000000000000000 '
1"
#780000
0"
#790000
b1000110000000000000000000000000 '
1"
#800000
0"
#810000
b11111101 !
b11111101 &
b1001000000000000000000000000000 '
1"
#820000
0"
#830000
b11111100 !
b11111100 &
b1001010000000000000000000000000 '
1"
#840000
0"
#850000
b11111011 !
b11111011 &
b1001100000000000000000000000000 '
1"
#860000
0"
#870000
b11111001 !
b11111001 &
b1001110000000000000000000000000 '
1"
#880000
0"
#890000
b11110111 !
b11110111 &
b1010000000000000000000000000000 '
1"
#900000
0"
#910000
b11110101 !
b11110101 &
b1010010000000000000000000000000 '
1"
#920000
0"
#930000
b11110010 !
b11110010 &
b1010100000000000000000000000000 '
1"
#940000
0"
#950000
b11110000 !
b11110000 &
b1010110000000000000000000000000 '
1"
#960000
0"
#970000
b11101100 !
b11101100 &
b1011000000000000000000000000000 '
1"
#980000
0"
#990000
b11101001 !
b11101001 &
b1011010000000000000000000000000 '
1"
#1000000
0"
#1010000
b11100110 !
b11100110 &
b1011100000000000000000000000000 '
1"
#1020000
0"
#1030000
b11100010 !
b11100010 &
b1011110000000000000000000000000 '
1"
#1040000
0"
#1050000
b11011110 !
b11011110 &
b1100000000000000000000000000000 '
1"
#1060000
0"
#1070000
b11011001 !
b11011001 &
b1100010000000000000000000000000 '
1"
#1080000
0"
#1090000
b11010101 !
b11010101 &
b1100100000000000000000000000000 '
1"
#1100000
0"
#1110000
b11010000 !
b11010000 &
b1100110000000000000000000000000 '
1"
#1120000
0"
#1130000
b11001011 !
b11001011 &
b1101000000000000000000000000000 '
1"
#1140000
0"
#1150000
b11000110 !
b11000110 &
b1101010000000000000000000000000 '
1"
#1160000
0"
#1170000
b11000001 !
b11000001 &
b1101100000000000000000000000000 '
1"
#1180000
0"
#1190000
b10111011 !
b10111011 &
b1101110000000000000000000000000 '
1"
#1200000
0"
#1210000
b10110110 !
b10110110 &
b1110000000000000000000000000000 '
1"
#1220000
0"
#1230000
b10110000 !
b10110000 &
b1110010000000000000000000000000 '
1"
#1240000
0"
#1250000
b10101010 !
b10101010 &
b1110100000000000000000000000000 '
1"
#1260000
0"
#1270000
b10100100 !
b10100100 &
b1110110000000000000000000000000 '
1"
#1280000
0"
#1290000
b10011110 !
b10011110 &
b1111000000000000000000000000000 '
1"
#1300000
0"
#1310000
b10011000 !
b10011000 &
b1111010000000000000000000000000 '
1"
#1320000
0"
#1330000
b10010010 !
b10010010 &
b1111100000000000000000000000000 '
1"
#1340000
0"
#1350000
b10001100 !
b10001100 &
b1111110000000000000000000000000 '
1"
#1360000
0"
#1370000
b10000110 !
b10000110 &
b10000000000000000000000000000000 '
1"
#1380000
0"
#1390000
b10000000 !
b10000000 &
b10000010000000000000000000000000 '
1"
#1400000
0"
#1410000
b1111001 !
b1111001 &
b10000100000000000000000000000000 '
1"
#1420000
0"
#1430000
b1110011 !
b1110011 &
b10000110000000000000000000000000 '
1"
#1440000
0"
#1450000
b1101101 !
b1101101 &
b10001000000000000000000000000000 '
1"
#1460000
0"
#1470000
b1100111 !
b1100111 &
b10001010000000000000000000000000 '
1"
#1480000
0"
#1490000
b1100001 !
b1100001 &
b10001100000000000000000000000000 '
1"
#1500000
0"
#1510000
b1011011 !
b1011011 &
b10001110000000000000000000000000 '
1"
#1520000
0"
#1530000
b1010101 !
b1010101 &
b10010000000000000000000000000000 '
1"
#1540000
0"
#1550000
b1001111 !
b1001111 &
b10010010000000000000000000000000 '
1"
#1560000
0"
#1570000
b1001001 !
b1001001 &
b10010100000000000000000000000000 '
1"
#1580000
0"
#1590000
b1000100 !
b1000100 &
b10010110000000000000000000000000 '
1"
#1600000
0"
#1610000
b111110 !
b111110 &
b10011000000000000000000000000000 '
1"
#1620000
0"
#1630000
b111001 !
b111001 &
b10011010000000000000000000000000 '
1"
#1640000
0"
#1650000
b110100 !
b110100 &
b10011100000000000000000000000000 '
1"
#1660000
0"
#1670000
b101111 !
b101111 &
b10011110000000000000000000000000 '
1"
#1680000
0"
#1690000
b101010 !
b101010 &
b10100000000000000000000000000000 '
1"
#1700000
0"
#1710000
b100110 !
b100110 &
b10100010000000000000000000000000 '
1"
#1720000
0"
#1730000
b100001 !
b100001 &
b10100100000000000000000000000000 '
1"
#1740000
0"
#1750000
b11101 !
b11101 &
b10100110000000000000000000000000 '
1"
#1760000
0"
#1770000
b11001 !
b11001 &
b10101000000000000000000000000000 '
1"
#1780000
0"
#1790000
b10110 !
b10110 &
b10101010000000000000000000000000 '
1"
#1800000
0"
#1810000
b10011 !
b10011 &
b10101100000000000000000000000000 '
1"
#1820000
0"
#1830000
b1111 !
b1111 &
b10101110000000000000000000000000 '
1"
#1840000
0"
#1850000
b1101 !
b1101 &
b10110000000000000000000000000000 '
1"
#1860000
0"
#1870000
b1010 !
b1010 &
b10110010000000000000000000000000 '
1"
#1880000
0"
#1890000
b1000 !
b1000 &
b10110100000000000000000000000000 '
1"
#1900000
0"
#1910000
b110 !
b110 &
b10110110000000000000000000000000 '
1"
#1920000
0"
#1930000
b100 !
b100 &
b10111000000000000000000000000000 '
1"
#1940000
0"
#1950000
b11 !
b11 &
b10111010000000000000000000000000 '
1"
#1960000
0"
#1970000
b10 !
b10 &
b10111100000000000000000000000000 '
1"
#1980000
0"
#1990000
b1 !
b1 &
b10111110000000000000000000000000 '
1"
#2000000
0"
#2010000
b11000000000000000000000000000000 '
1"
#2020000
0"
#2030000
b11000010000000000000000000000000 '
1"
#2040000
0"
#2050000
b11000100000000000000000000000000 '
1"
#2060000
0"
#2070000
b11000110000000000000000000000000 '
1"
#2080000
0"
#2090000
b10 !
b10 &
b11001000000000000000000000000000 '
1"
#2100000
0"
#2110000
b11 !
b11 &
b11001010000000000000000000000000 '
1"
#2120000
0"
#2130000
b100 !
b100 &
b11001100000000000000000000000000 '
1"
#2140000
0"
#2150000
b110 !
b110 &
b11001110000000000000000000000000 '
1"
#2160000
0"
#2170000
b1000 !
b1000 &
b11010000000000000000000000000000 '
1"
#2180000
0"
#2190000
b1010 !
b1010 &
b11010010000000000000000000000000 '
1"
#2200000
0"
#2210000
b1101 !
b1101 &
b11010100000000000000000000000000 '
1"
#2220000
0"
#2230000
b1111 !
b1111 &
b11010110000000000000000000000000 '
1"
#2240000
0"
#2250000
b10011 !
b10011 &
b11011000000000000000000000000000 '
1"
#2260000
0"
#2270000
b10110 !
b10110 &
b11011010000000000000000000000000 '
1"
#2280000
0"
#2290000
b11001 !
b11001 &
b11011100000000000000000000000000 '
1"
#2300000
0"
#2310000
b11101 !
b11101 &
b11011110000000000000000000000000 '
1"
#2320000
0"
#2330000
b100001 !
b100001 &
b11100000000000000000000000000000 '
1"
#2340000
0"
#2350000
b100110 !
b100110 &
b11100010000000000000000000000000 '
1"
#2360000
0"
#2370000
b101010 !
b101010 &
b11100100000000000000000000000000 '
1"
#2380000
0"
#2390000
b101111 !
b101111 &
b11100110000000000000000000000000 '
1"
#2400000
0"
#2410000
b110100 !
b110100 &
b11101000000000000000000000000000 '
1"
#2420000
0"
#2430000
b111001 !
b111001 &
b11101010000000000000000000000000 '
1"
#2440000
0"
#2450000
b111110 !
b111110 &
b11101100000000000000000000000000 '
1"
#2460000
0"
#2470000
b1000100 !
b1000100 &
b11101110000000000000000000000000 '
1"
#2480000
0"
#2490000
b1001001 !
b1001001 &
b11110000000000000000000000000000 '
1"
#2500000
0"
#2510000
b1001111 !
b1001111 &
b11110010000000000000000000000000 '
1"
#2520000
0"
#2530000
b1010101 !
b1010101 &
b11110100000000000000000000000000 '
1"
#2540000
0"
#2550000
b1011011 !
b1011011 &
b11110110000000000000000000000000 '
1"
#2560000
0"
#2570000
b1100001 !
b1100001 &
b11111000000000000000000000000000 '
1"
#2580000
0"
#2590000
b1100111 !
b1100111 &
b11111010000000000000000000000000 '
1"
#2600000
0"
#2610000
b1101101 !
b1101101 &
b11111100000000000000000000000000 '
1"
#2620000
0"
#2630000
b1110011 !
b1110011 &
b11111110000000000000000000000000 '
1"
#2640000
0"
#2650000
b1111001 !
b1111001 &
b0 '
1"
#2660000
0"
#2670000
b10000000 !
b10000000 &
b10000000000000000000000000 '
1"
#2680000
0"
#2690000
b10000110 !
b10000110 &
b100000000000000000000000000 '
1"
#2700000
0"
#2710000
b10001100 !
b10001100 &
b110000000000000000000000000 '
1"
#2720000
0"
#2730000
b10010010 !
b10010010 &
b1000000000000000000000000000 '
1"
#2740000
0"
#2750000
b10011000 !
b10011000 &
b1010000000000000000000000000 '
1"
#2760000
0"
#2770000
b10011110 !
b10011110 &
b1100000000000000000000000000 '
1"
#2780000
0"
#2790000
b10100100 !
b10100100 &
b1110000000000000000000000000 '
1"
#2800000
0"
#2810000
b10101010 !
b10101010 &
b10000000000000000000000000000 '
1"
#2820000
0"
#2830000
b10110000 !
b10110000 &
b10010000000000000000000000000 '
1"
#2840000
0"
#2850000
b10110110 !
b10110110 &
b10100000000000000000000000000 '
1"
#2860000
0"
#2870000
b10111011 !
b10111011 &
b10110000000000000000000000000 '
1"
#2880000
0"
#2890000
b11000001 !
b11000001 &
b11000000000000000000000000000 '
1"
#2900000
0"
#2910000
b11000110 !
b11000110 &
b11010000000000000000000000000 '
1"
#2920000
0"
#2930000
b11001011 !
b11001011 &
b11100000000000000000000000000 '
1"
#2940000
0"
#2950000
b11010000 !
b11010000 &
b11110000000000000000000000000 '
1"
#2960000
0"
#2970000
b11010101 !
b11010101 &
b100000000000000000000000000000 '
1"
#2980000
0"
#2990000
b11011001 !
b11011001 &
b100010000000000000000000000000 '
1"
#3000000
0"
#3010000
b11011110 !
b11011110 &
b100100000000000000000000000000 '
1"
#3020000
0"
#3030000
b11100010 !
b11100010 &
b100110000000000000000000000000 '
1"
#3040000
0"
#3050000
b11100110 !
b11100110 &
b101000000000000000000000000000 '
1"
#3060000
0"
#3070000
b11101001 !
b11101001 &
b101010000000000000000000000000 '
1"
#3080000
0"
#3090000
b11101100 !
b11101100 &
b101100000000000000000000000000 '
1"
#3100000
0"
#3110000
b11110000 !
b11110000 &
b101110000000000000000000000000 '
1"
#3120000
0"
#3130000
b11110010 !
b11110010 &
b110000000000000000000000000000 '
1"
#3140000
0"
#3150000
b11110101 !
b11110101 &
b110010000000000000000000000000 '
1"
#3160000
0"
#3170000
b11110111 !
b11110111 &
b110100000000000000000000000000 '
1"
#3180000
0"
#3190000
b11111001 !
b11111001 &
b110110000000000000000000000000 '
1"
#3200000
0"
#3210000
b11111011 !
b11111011 &
b111000000000000000000000000000 '
1"
#3220000
0"
#3230000
b11111100 !
b11111100 &
b111010000000000000000000000000 '
1"
#3240000
0"
#3250000
b11111101 !
b11111101 &
b111100000000000000000000000000 '
1"
#3260000
0"
#3270000
b11111110 !
b11111110 &
b111110000000000000000000000000 '
1"
#3280000
0"
#3290000
b1000000000000000000000000000000 '
1"
#3300000
0"
#3310000
b11111111 !
b11111111 &
b1000010000000000000000000000000 '
1"
#3320000
0"
#3330000
b11111110 !
b11111110 &
b1000100000000000000000000000000 '
1"
#3340000
0"
#3350000
b1000110000000000000000000000000 '
1"
#3360000
0"
#3370000
b11111101 !
b11111101 &
b1001000000000000000000000000000 '
1"
#3380000
0"
#3390000
b11111100 !
b11111100 &
b1001010000000000000000000000000 '
1"
#3400000
0"
#3410000
b11111011 !
b11111011 &
b1001100000000000000000000000000 '
1"
#3420000
0"
#3430000
b11111001 !
b11111001 &
b1001110000000000000000000000000 '
1"
#3440000
0"
#3450000
b11110111 !
b11110111 &
b1010000000000000000000000000000 '
1"
#3460000
0"
#3470000
b11110101 !
b11110101 &
b1010010000000000000000000000000 '
1"
#3480000
0"
#3490000
b11110010 !
b11110010 &
b1010100000000000000000000000000 '
1"
#3500000
0"
#3510000
b11110000 !
b11110000 &
b1010110000000000000000000000000 '
1"
#3520000
0"
#3530000
b11101100 !
b11101100 &
b1011000000000000000000000000000 '
1"
#3540000
0"
#3550000
b11101001 !
b11101001 &
b1011010000000000000000000000000 '
1"
#3560000
0"
#3570000
b11100110 !
b11100110 &
b1011100000000000000000000000000 '
1"
#3580000
0"
#3590000
b11100010 !
b11100010 &
b1011110000000000000000000000000 '
1"
#3600000
0"
#3610000
b11011110 !
b11011110 &
b1100000000000000000000000000000 '
1"
#3620000
0"
#3630000
b11011001 !
b11011001 &
b1100010000000000000000000000000 '
1"
#3640000
0"
#3650000
b11010101 !
b11010101 &
b1100100000000000000000000000000 '
1"
#3660000
0"
#3670000
b11010000 !
b11010000 &
b1100110000000000000000000000000 '
1"
#3680000
0"
#3690000
b11001011 !
b11001011 &
b1101000000000000000000000000000 '
1"
#3700000
0"
#3710000
b11000110 !
b11000110 &
b1101010000000000000000000000000 '
1"
#3720000
0"
#3730000
b11000001 !
b11000001 &
b1101100000000000000000000000000 '
1"
#3740000
0"
#3750000
b10111011 !
b10111011 &
b1101110000000000000000000000000 '
1"
#3760000
0"
#3770000
b10110110 !
b10110110 &
b1110000000000000000000000000000 '
1"
#3780000
0"
#3790000
b10110000 !
b10110000 &
b1110010000000000000000000000000 '
1"
#3800000
0"
#3810000
b10101010 !
b10101010 &
b1110100000000000000000000000000 '
1"
#3820000
0"
#3830000
b10100100 !
b10100100 &
b1110110000000000000000000000000 '
1"
#3840000
0"
#3850000
b10011110 !
b10011110 &
b1111000000000000000000000000000 '
1"
#3860000
0"
#3870000
b10011000 !
b10011000 &
b1111010000000000000000000000000 '
1"
#3880000
0"
#3890000
b10010010 !
b10010010 &
b1111100000000000000000000000000 '
1"
#3900000
0"
#3910000
b10001100 !
b10001100 &
b1111110000000000000000000000000 '
1"
#3920000
0"
#3930000
b10000110 !
b10000110 &
b10000000000000000000000000000000 '
1"
#3940000
0"
#3950000
b10000000 !
b10000000 &
b10000010000000000000000000000000 '
1"
#3960000
0"
#3970000
b1111001 !
b1111001 &
b10000100000000000000000000000000 '
1"
#3980000
0"
#3990000
b1110011 !
b1110011 &
b10000110000000000000000000000000 '
1"
#4000000
0"
#4010000
b1101101 !
b1101101 &
b10001000000000000000000000000000 '
1"
#4020000
0"
#4030000
b1100111 !
b1100111 &
b10001010000000000000000000000000 '
1"
#4040000
0"
#4050000
b1100001 !
b1100001 &
b10001100000000000000000000000000 '
1"
#4060000
0"
#4070000
b1011011 !
b1011011 &
b10001110000000000000000000000000 '
1"
#4080000
0"
#4090000
b1010101 !
b1010101 &
b10010000000000000000000000000000 '
1"
#4100000
0"
#4110000
b1001111 !
b1001111 &
b10010010000000000000000000000000 '
1"
#4120000
0"
#4130000
b1001001 !
b1001001 &
b10010100000000000000000000000000 '
1"
#4140000
0"
#4150000
b1000100 !
b1000100 &
b10010110000000000000000000000000 '
1"
#4160000
0"
#4170000
b111110 !
b111110 &
b10011000000000000000000000000000 '
1"
#4180000
0"
#4190000
b111001 !
b111001 &
b10011010000000000000000000000000 '
1"
#4200000
0"
#4210000
b110100 !
b110100 &
b10011100000000000000000000000000 '
1"
#4220000
0"
#4230000
b101111 !
b101111 &
b10011110000000000000000000000000 '
1"
#4240000
0"
#4250000
b101010 !
b101010 &
b10100000000000000000000000000000 '
1"
#4260000
0"
#4270000
b100110 !
b100110 &
b10100010000000000000000000000000 '
1"
#4280000
0"
#4290000
b100001 !
b100001 &
b10100100000000000000000000000000 '
1"
#4300000
0"
#4310000
b11101 !
b11101 &
b10100110000000000000000000000000 '
1"
#4320000
0"
#4330000
b11001 !
b11001 &
b10101000000000000000000000000000 '
1"
#4340000
0"
#4350000
b10110 !
b10110 &
b10101010000000000000000000000000 '
1"
#4360000
0"
#4370000
b10011 !
b10011 &
b10101100000000000000000000000000 '
1"
#4380000
0"
#4390000
b1111 !
b1111 &
b10101110000000000000000000000000 '
1"
#4400000
0"
#4410000
b1101 !
b1101 &
b10110000000000000000000000000000 '
1"
#4420000
0"
#4430000
b1010 !
b1010 &
b10110010000000000000000000000000 '
1"
#4440000
0"
#4450000
b1000 !
b1000 &
b10110100000000000000000000000000 '
1"
#4460000
0"
#4470000
b110 !
b110 &
b10110110000000000000000000000000 '
1"
#4480000
0"
#4490000
b100 !
b100 &
b10111000000000000000000000000000 '
1"
#4500000
0"
#4510000
b11 !
b11 &
b10111010000000000000000000000000 '
1"
#4520000
0"
#4530000
b10 !
b10 &
b10111100000000000000000000000000 '
1"
#4540000
0"
#4550000
b1 !
b1 &
b10111110000000000000000000000000 '
1"
#4560000
0"
#4570000
b11000000000000000000000000000000 '
1"
#4580000
0"
#4590000
b11000010000000000000000000000000 '
1"
#4600000
0"
#4610000
b11000100000000000000000000000000 '
1"
#4620000
0"
#4630000
b11000110000000000000000000000000 '
1"
#4640000
0"
#4650000
b10 !
b10 &
b11001000000000000000000000000000 '
1"
#4660000
0"
#4670000
b11 !
b11 &
b11001010000000000000000000000000 '
1"
#4680000
0"
#4690000
b100 !
b100 &
b11001100000000000000000000000000 '
1"
#4700000
0"
#4710000
b110 !
b110 &
b11001110000000000000000000000000 '
1"
#4720000
0"
#4730000
b1000 !
b1000 &
b11010000000000000000000000000000 '
1"
#4740000
0"
#4750000
b1010 !
b1010 &
b11010010000000000000000000000000 '
1"
#4760000
0"
#4770000
b1101 !
b1101 &
b11010100000000000000000000000000 '
1"
#4780000
0"
#4790000
b1111 !
b1111 &
b11010110000000000000000000000000 '
1"
#4800000
0"
#4810000
b10011 !
b10011 &
b11011000000000000000000000000000 '
1"
#4820000
0"
#4830000
b10110 !
b10110 &
b11011010000000000000000000000000 '
1"
#4840000
0"
#4850000
b11001 !
b11001 &
b11011100000000000000000000000000 '
1"
#4860000
0"
#4870000
b11101 !
b11101 &
b11011110000000000000000000000000 '
1"
#4880000
0"
#4890000
b100001 !
b100001 &
b11100000000000000000000000000000 '
1"
#4900000
0"
#4910000
b100110 !
b100110 &
b11100010000000000000000000000000 '
1"
#4920000
0"
#4930000
b101010 !
b101010 &
b11100100000000000000000000000000 '
1"
#4940000
0"
#4950000
b101111 !
b101111 &
b11100110000000000000000000000000 '
1"
#4960000
0"
#4970000
b110100 !
b110100 &
b11101000000000000000000000000000 '
1"
#4980000
0"
#4990000
b111001 !
b111001 &
b11101010000000000000000000000000 '
1"
#5000000
0"
#5010000
b111110 !
b111110 &
b11101100000000000000000000000000 '
1"
#5020000
0"
#5030000
b1000100 !
b1000100 &
b11101110000000000000000000000000 '
1"
#5040000
0"
#5050000
b1001001 !
b1001001 &
b11110000000000000000000000000000 '
1"
#5060000
0"
#5070000
b1001111 !
b1001111 &
b11110010000000000000000000000000 '
1"
#5080000
0"
#5090000
b1010101 !
b1010101 &
b11110100000000000000000000000000 '
1"
#5100000
0"
#5110000
b1011011 !
b1011011 &
b11110110000000000000000000000000 '
1"
#5120000
0"
#5130000
b1100001 !
b1100001 &
b11111000000000000000000000000000 '
1"
#5140000
0"
#5150000
b1100111 !
b1100111 &
b11111010000000000000000000000000 '
1"
#5160000
0"
#5170000
b1101101 !
b1101101 &
b11111100000000000000000000000000 '
1"
#5180000
0"
#5190000
b1110011 !
b1110011 &
b11111110000000000000000000000000 '
1"
#5200000
0"
#5210000
b1111001 !
b1111001 &
b0 '
1"
#5220000
0"
#5230000
b10000000 !
b10000000 &
b10000000000000000000000000 '
1"
#5240000
0"
#5250000
b10000110 !
b10000110 &
b100000000000000000000000000 '
1"
#5260000
0"
#5270000
b10001100 !
b10001100 &
b110000000000000000000000000 '
1"
#5280000
0"
#5290000
b10010010 !
b10010010 &
b1000000000000000000000000000 '
1"
#5300000
0"
#5310000
b10011000 !
b10011000 &
b1010000000000000000000000000 '
1"
#5320000
0"
#5330000
b10011110 !
b10011110 &
b1100000000000000000000000000 '
1"
#5340000
0"
#5350000
b10100100 !
b10100100 &
b1110000000000000000000000000 '
1"
#5360000
0"
#5370000
b10101010 !
b10101010 &
b10000000000000000000000000000 '
1"
#5380000
0"
#5390000
b10110000 !
b10110000 &
b10010000000000000000000000000 '
1"
#5400000
0"
#5410000
b10110110 !
b10110110 &
b10100000000000000000000000000 '
1"
#5420000
0"
#5430000
b10111011 !
b10111011 &
b10110000000000000000000000000 '
1"
#5440000
0"
#5450000
b11000001 !
b11000001 &
b11000000000000000000000000000 '
1"
#5460000
0"
#5470000
b11000110 !
b11000110 &
b11010000000000000000000000000 '
1"
#5480000
0"
#5490000
b11001011 !
b11001011 &
b11100000000000000000000000000 '
1"
#5500000
0"
#5510000
b11010000 !
b11010000 &
b11110000000000000000000000000 '
1"
#5520000
0"
#5530000
b11010101 !
b11010101 &
b100000000000000000000000000000 '
1"
#5540000
0"
#5550000
b11011001 !
b11011001 &
b100010000000000000000000000000 '
1"
#5560000
0"
#5570000
b11011110 !
b11011110 &
b100100000000000000000000000000 '
1"
#5580000
0"
#5590000
b11100010 !
b11100010 &
b100110000000000000000000000000 '
1"
#5600000
0"
#5610000
b11100110 !
b11100110 &
b101000000000000000000000000000 '
1"
#5620000
0"
#5630000
b11101001 !
b11101001 &
b101010000000000000000000000000 '
1"
#5640000
0"
#5650000
b11101100 !
b11101100 &
b101100000000000000000000000000 '
1"
#5660000
0"
#5670000
b11110000 !
b11110000 &
b101110000000000000000000000000 '
1"
#5680000
0"
#5690000
b11110010 !
b11110010 &
b110000000000000000000000000000 '
1"
#5700000
0"
#5710000
b11110101 !
b11110101 &
b110010000000000000000000000000 '
1"
#5720000
0"
#5730000
b11110111 !
b11110111 &
b110100000000000000000000000000 '
1"
#5740000
0"
#5750000
b11111001 !
b11111001 &
b110110000000000000000000000000 '
1"
#5760000
0"
#5770000
b11111011 !
b11111011 &
b111000000000000000000000000000 '
1"
#5780000
0"
#5790000
b11111100 !
b11111100 &
b111010000000000000000000000000 '
1"
#5800000
0"
#5810000
b11111101 !
b11111101 &
b111100000000000000000000000000 '
1"
#5820000
0"
#5830000
b11111110 !
b11111110 &
b111110000000000000000000000000 '
1"
#5840000
0"
#5850000
b1000000000000000000000000000000 '
1"
#5860000
0"
#5870000
b11111111 !
b11111111 &
b1000010000000000000000000000000 '
1"
#5880000
0"
#5890000
b11111110 !
b11111110 &
b1000100000000000000000000000000 '
1"
#5900000
0"
#5910000
b1000110000000000000000000000000 '
1"
#5920000
0"
#5930000
b11111101 !
b11111101 &
b1001000000000000000000000000000 '
1"
#5940000
0"
#5950000
b11111100 !
b11111100 &
b1001010000000000000000000000000 '
1"
#5960000
0"
#5970000
b11111011 !
b11111011 &
b1001100000000000000000000000000 '
1"
#5980000
0"
#5990000
b11111001 !
b11111001 &
b1001110000000000000000000000000 '
1"
#6000000
0"
#6010000
b11110111 !
b11110111 &
b1010000000000000000000000000000 '
1"
#6020000
0"
#6030000
b11110101 !
b11110101 &
b1010010000000000000000000000000 '
1"
#6040000
0"
#6050000
b11110010 !
b11110010 &
b1010100000000000000000000000000 '
1"
#6060000
0"
#6070000
b11110000 !
b11110000 &
b1010110000000000000000000000000 '
1"
#6080000
0"
#6090000
b11101100 !
b11101100 &
b1011000000000000000000000000000 '
1"
#6100000
0"
#6110000
b11101001 !
b11101001 &
b1011010000000000000000000000000 '
1"
#6120000
0"
#6130000
b11100110 !
b11100110 &
b1011100000000000000000000000000 '
1"
#6140000
0"
#6150000
b11100010 !
b11100010 &
b1011110000000000000000000000000 '
1"
#6160000
0"
#6170000
b11011110 !
b11011110 &
b1100000000000000000000000000000 '
1"
#6180000
0"
#6190000
b11011001 !
b11011001 &
b1100010000000000000000000000000 '
1"
#6200000
0"
#6210000
b11010101 !
b11010101 &
b1100100000000000000000000000000 '
1"
#6220000
0"
#6230000
b11010000 !
b11010000 &
b1100110000000000000000000000000 '
1"
#6240000
0"
#6250000
b11001011 !
b11001011 &
b1101000000000000000000000000000 '
1"
#6260000
0"
#6270000
b11000110 !
b11000110 &
b1101010000000000000000000000000 '
1"
#6280000
0"
#6290000
b11000001 !
b11000001 &
b1101100000000000000000000000000 '
1"
#6300000
0"
#6310000
b10111011 !
b10111011 &
b1101110000000000000000000000000 '
1"
#6320000
0"
#6330000
b10110110 !
b10110110 &
b1110000000000000000000000000000 '
1"
#6340000
0"
#6350000
b10110000 !
b10110000 &
b1110010000000000000000000000000 '
1"
#6360000
0"
#6370000
b10101010 !
b10101010 &
b1110100000000000000000000000000 '
1"
#6380000
0"
#6390000
b10100100 !
b10100100 &
b1110110000000000000000000000000 '
1"
#6400000
0"
